tupas_verisigner.py
tupas_verisigner-0.0.1.dist-info/LICENSE
tupas_verisigner-0.0.1.dist-info/METADATA
tupas_verisigner-0.0.1.dist-info/WHEEL
tupas_verisigner-0.0.1.dist-info/top_level.txt
tupas_verisigner-0.0.1.dist-info/RECORD
