Metadata-Version: 2.1
Name: tupas-verisigner
Version: 0.0.1
Summary: TUPAS URL verification and signing
Home-page: http://github.com/adarshk7/tupas_verisigner
Author: Adarsh Krishnan
Author-email: adarshk7@gmail.com
License: MIT
Platform: UNKNOWN
Classifier: Development Status :: 4 - Beta
Classifier: Intended Audience :: Developers
Classifier: Natural Language :: English
Classifier: License :: OSI Approved :: MIT License
Classifier: Programming Language :: Python
Classifier: Programming Language :: Python :: 3.5
Classifier: Programming Language :: Python :: 3.6
Classifier: Programming Language :: Python :: 3.7
Requires-Python: >=3.5
